{"data":{"Year":[2017,2018,2019,2020,2021,2017,2018,2019,2020,2021,2017,2018,2019,2020,2021,2017,2018,2019,2020,2021,2017,2018,2019,2020,2021,2017,2018,2019,2020,2021,2017,2018,2019,2020,2021],"Site":["St Helens  Linkway","St Helens  Linkway","St Helens  Linkway","St Helens  Linkway","St Helens  Linkway","St Helens  Linkway","St Helens  Linkway","St Helens  Linkway","St Helens  Linkway","St Helens  Linkway","St Helens  Linkway","St Helens  Linkway","St Helens  Linkway","St Helens  Linkway","St Helens  Linkway","St Helens  Linkway","St Helens  Linkway","St Helens  Linkway","St Helens  Linkway","St Helens  Linkway","St Helens  Linkway","St Helens  Linkway","St Helens  Linkway","St Helens  Linkway","St Helens  Linkway","St Helens  Linkway","St Helens  Linkway","St Helens  Linkway","St Helens  Linkway","St Helens  Linkway","St Helens  Linkway","St Helens  Linkway","St Helens  Linkway","St Helens  Linkway","St Helens  Linkway"],"Type":["1 Moderate","2 Moderate","3 Moderate","1 High","2 High","3 High","Very High","1 Moderate","2 Moderate","3 Moderate","1 High","2 High","3 High","Very High","1 Moderate","2 Moderate","3 Moderate","1 High","2 High","3 High","Very High","1 Moderate","2 Moderate","3 Moderate","1 High","2 High","3 High","Very High","1 Moderate","2 Moderate","3 Moderate","1 High","2 High","3 High","Very High"],"Value":[31,2,31,0,0,0,0,97,2,0,0,0,0,0,21,13,20,0,0,0,24,10,40,0,0,2,0,0,50,7,10,0,0,0,0]},"edges":{"From":["Site"],"To":["Type"]}}